odoo9_addon_product_multi_company-9.0.1.0.1-nspkg.pth
odoo_addons/product_multi_company/README.rst
odoo_addons/product_multi_company/__init__.py
odoo_addons/product_multi_company/__openerp__.py
odoo_addons/product_multi_company/hooks.py
odoo_addons/product_multi_company/i18n/de.po
odoo_addons/product_multi_company/i18n/es.po
odoo_addons/product_multi_company/i18n/fr.po
odoo_addons/product_multi_company/i18n/product_multi_company.pot
odoo_addons/product_multi_company/models/__init__.py
odoo_addons/product_multi_company/models/product_template.py
odoo_addons/product_multi_company/static/description/icon.png
odoo_addons/product_multi_company/tests/__init__.py
odoo_addons/product_multi_company/tests/test_product_multi_company.py
odoo_addons/product_multi_company/views/product_template_view.xml
odoo9_addon_product_multi_company-9.0.1.0.1.dist-info/METADATA
odoo9_addon_product_multi_company-9.0.1.0.1.dist-info/WHEEL
odoo9_addon_product_multi_company-9.0.1.0.1.dist-info/namespace_packages.txt
odoo9_addon_product_multi_company-9.0.1.0.1.dist-info/top_level.txt
odoo9_addon_product_multi_company-9.0.1.0.1.dist-info/RECORD
